ctxai/__init__.py
ctxai/__main__.py
ctxai/app.py
ctxai/chunking.py
ctxai/config.py
ctxai/embeddings.py
ctxai/server.py
ctxai/size_validator.py
ctxai/traversal.py
ctxai/utils.py
ctxai/vector_store.py
ctxai/commands/__init__.py
ctxai/commands/config_command.py
ctxai/commands/dashboard_command.py
ctxai/commands/index_command.py
ctxai/commands/query_command.py
ctxai/commands/server_command.py
ctxai-0.0.2.dist-info/METADATA
ctxai-0.0.2.dist-info/WHEEL
ctxai-0.0.2.dist-info/entry_points.txt
ctxai-0.0.2.dist-info/licenses/LICENSE
ctxai-0.0.2.dist-info/RECORD
