Metadata-Version: 2.4
Name: ctxai
Version: 0.0.2
Author-email: vs4vijay <vs4vijay@gmail.com>
License-Expression: MIT
License-File: LICENSE
Requires-Python: >=3.10
Requires-Dist: chromadb>=0.5.0
Requires-Dist: pathspec>=0.12.1
Requires-Dist: pydantic-ai>=1.0.15
Requires-Dist: pydantic>=2.11.10
Requires-Dist: python-dotenv>=1.1.1
Requires-Dist: rich>=13.9.4
Requires-Dist: sentence-transformers>=3.3.1
Requires-Dist: tree-sitter-language-pack>=0.9.0
Requires-Dist: tree-sitter>=0.25.2
Requires-Dist: typer>=0.19.2
Provides-Extra: all
Requires-Dist: mcp>=1.16.0; extra == 'all'
Requires-Dist: openai>=1.58.1; extra == 'all'
Requires-Dist: python-fasthtml>=0.9.3; extra == 'all'
Provides-Extra: dashboard
Requires-Dist: python-fasthtml>=0.9.3; extra == 'dashboard'
Provides-Extra: mcp
Requires-Dist: mcp>=1.16.0; extra == 'mcp'
Provides-Extra: openai
Requires-Dist: openai>=1.58.1; extra == 'openai'
